gridlock/LICENSE.md
gridlock/README.md
gridlock/__init__.py
gridlock/base.py
gridlock/draw.py
gridlock/grid.py
gridlock/position.py
gridlock/py.typed
gridlock/read.py
gridlock/utils.py
gridlock/examples/ex0.py
gridlock/test/__init__.py
gridlock/test/test_grid.py
gridlock-2.0.dist-info/METADATA
gridlock-2.0.dist-info/WHEEL
gridlock-2.0.dist-info/licenses/LICENSE.md
gridlock-2.0.dist-info/RECORD
