Metadata-Version: 2.4
Name: gridlock
Version: 2.0
Summary: Coupled gridding library
Author-email: Jan Petykiewicz <jan@mpxd.net>
License: GNU Affero General Public License
License-File: LICENSE.md
Keywords: FDFD,FDTD,difference,finite,gridding,nonuniform,simulation
Classifier: Development Status :: 4 - Beta
Classifier: Intended Audience :: Developers
Classifier: Intended Audience :: Science/Research
Classifier: License :: OSI Approved :: GNU Affero General Public License v3
Classifier: Programming Language :: Python :: 3
Classifier: Topic :: Multimedia :: Graphics :: 3D Rendering
Classifier: Topic :: Scientific/Engineering :: Electronic Design Automation (EDA)
Classifier: Topic :: Scientific/Engineering :: Physics
Classifier: Topic :: Scientific/Engineering :: Visualization
Requires-Python: >=3.11
Requires-Dist: float-raster>=0.8
Requires-Dist: numpy>=1.26
Provides-Extra: visualization
Requires-Dist: matplotlib; extra == 'visualization'
Provides-Extra: visualization-isosurface
Requires-Dist: matplotlib; extra == 'visualization-isosurface'
Requires-Dist: mpl-toolkits; extra == 'visualization-isosurface'
Requires-Dist: skimage>=0.13; extra == 'visualization-isosurface'
